{
    "cpu": {
        "B0DJ2TH7QF": "BRENUC NUC 11 Extreme Kit Beast Canyon NUC11BTMi7 Intel Core i7-11700B Gaming PC Barebone",
        "B0BQ6BCWC4": "Intel i3-13100F processor",
        "B0CCS5VFQF": "2bay nas quad core cpu ddr4 ram personal private cloud home network attached storage with backup solutions",
        "B0DLBFLVR8": "CPU holder for desktop and wall mount",
        "B0CK2R6DVS": "AMD Ryzen Threadripper Processor",
        "B0CK2ZQJZ6": "AMD Ryzen Threadripper PRO processor",
        "B0CDKKS5S1": "240mm liquid cpu cooler",
        "B0BK539D4V": "gaming desktop computer",
        "B0BDLYSB1B": "AMD FX6300 CPU Processor",
        "B07PB94X3R": "Intel Core i7-8700 CPU",
        "B0CGJDBCTK": "Intel Core i9 Gaming Desktop Processor 24 cores",
        "B0DFK2MH2D": "Intel Core Ultra 7 Desktop Processor",
        "B0CQ27H8VY": "Intel Core i5 Desktop Processor",
        "B07BCGW85X": "HP ProDesk 600 G1 SFF Business Desktop Computer",
        "B0CCG8S1VL": "ASUS ROG Strix 1000W Gold Aura Edition Power Supply",
        "B08166SLDF": "AMD Ryzen 5 5600X processor",
        "B0DCFNKXKY": "NZXT Kraken Elite 240 RGB CPU Liquid Cooler",
        "B0CP8P42T3": "Radeon RX 580 graphics card for gaming PC",
        "B0DF7P4WTL": "Iota L24 Liquid CPU Cooler",
        "B0CQ1Y7KHV": "Intel Core i5 Processor 10 cores",
        "B0CNGTNB9R": "jumper laptop 14 inch",
        "B0BBHHT8LY": null,
        "B09FXDLX95": "Intel Core i9-12900K Gaming Processor",
        "B0B1JH951J": "PSU cable extension kit with combs",
        "B09MDGKQLY": "Intel Core i3-12100F Desktop Processor",
        "B091J3NYVF": "AMD Ryzen 7 5700G Processor with Radeon Graphics",
        "B0BTZB7F88": "AMD Ryzen 7 7800X3D Processor",
        "B0DJ8Q8D3W": "mini pc, 16gb ram, 512gb m.2 ssd, windows 11pro, alder lake n95 cpu",
        "B0BBHD5D8Y": "AMD Ryzen 9 desktop processor",
        "B0CQ1MN1Y2": "Intel Core i3 desktop processor",
        "B09RWL74GY": "Intel Core i9 processor",
        "B086ML4XSB": "Intel Core i7-10700K Processor",
        "B07STGHZK8": "AMD Ryzen 3 3200G processor with Radeon Graphics",
        "B0D9RJ4BS7": "mini pc with intel alder lake cpu",
        "B0D6NMCZG1": "AMD Ryzen processor",
        "B07S4MSXJL": "Intel Core i5 processor",
        "B0D6NNRBGP": "AMD Ryzen 9 9950X Processor",
        "B09FWYK5M9": "Intel Core i9-12900KF processor",
        "B099KSJN8P": "mini pc computers",
        "B0C4K7JQ13": "printer stand with storage",
        "B0BMQK718H": "AMD Ryzen 9 7900 Processor",
        "B0BCF54SR1": "Intel Core i9-13900K Processor with Integrated Graphics",
        "B0BW8JSQCH": "mini pc",
        "B0CHBJGFBC": "Intel Core i9-14900K Processor",
        "B08GYKYM4J": "dell poweredge server",
        "B0CQ4H4H7X": "AMD Ryzen 7 5700X3D Processor",
        "B0D2JCMP34": "AMD Ryzen 7 8700F",
        "B08BJDFZRF": "Dell Optiplex 9020 desktop",
        "B09NPHJLPT": "Intel Core i3 Processor",
        "B01MZZJ1P0": "Intel Core i5 processor",
        "B0BBJDS62N": "AMD Ryzen 5 7600X Processor",
        "B07K6YG7YY": "Dell Optiplex 7040 Business SFF Computer",
        "B09FXNVDBJ": "Intel Core i7-12700K Gaming Processor with Integrated Graphics and 12 (8P+4E) Cores",
        "B0DHXLX85K": "mini pc, intel core i3, 8gb ram, 256gb ssd, triple display, wifi 6, bt 5.2",
        "B092CCJ2GZ": "Intel Core i3-10105F Processor",
        "B0CQ4JBKW3": "AMD Ryzen 7 Processor",
        "B0CXDJDSGQ": "CPU motherboard bundle with Intel i7-12700KF processor and MSI PRO Z790-P WiFi motherboard",
        "B0CQ4GYTTX": "AMD Ryzen 5",
        "B0CVJG9ZVC": "Dell PowerEdge T320 Tower Server",
        "B0B8K3FQ2Q": "Dell PowerEdge T640 Server",
        "B09VCJ171S": "AMD Ryzen 5 5500 processor with Wraith Stealth Cooler",
        "B09FXFJW2F": "Intel Core i5 Desktop Processor",
        "B08X6PPTTH": "Intel Core i9 processor",
        "B0BBJ59WJ4": "AMD Ryzen 9 7900X processor",
        "B0BMQJWBDM": "AMD Ryzen 5 7600 desktop processor",
        "B0CQ1P2TRN": "Intel Core i7 processor",
        "B0DFKC99VL": "Intel Core Ultra 9 Processor",
        "B08X1KKVCZ": "dell optiplex desktop pc",
        "B08164VTWH": "AMD Ryzen 9 5900X Processor",
        "B09NPJRDGD": "Intel Core i5 processor",
        "B09FXKHN7M": "Intel Core i7 Gaming Desktop Processor",
        "B0DKFMSMYK": "AMD Ryzen 7 processor",
        "B0BG63WLG3": "Intel Core i5-13600K Processor",
        "B0D87DJPB7": "gaming mini pc with intel i9-12900H and geforce RTX 3050 Ti",
        "B09Z5NH6SJ": "AMD Ryzen 5 4600G processor",
        "B09FX4D72T": "Intel Core i5-12600K Processor with Integrated Graphics",
        "B0BCFM3CJ4": "Intel Core i9 Gaming Desktop Processor",
        "B0971HVYT9": "gaming pc, intel core i9, geforce rtx 4060 ti, 1tb nvme m.2 ssd, 4tb hdd, 32gb ddr4 rgb memory, 240mm aio,",
        "B0DBHL5461": "CPU motherboard and processor combo",
        "B09VCRQVWM": "AMD Ryzen 3 4100 processor with Wraith Stealth Cooler"
    }
}